astro_gspider/__init__.py
astro_gspider/hello.py
tests/__init__.py
astro_gspider-0.1.1.dist-info/LICENSE
astro_gspider-0.1.1.dist-info/METADATA
astro_gspider-0.1.1.dist-info/WHEEL
astro_gspider-0.1.1.dist-info/top_level.txt
astro_gspider-0.1.1.dist-info/RECORD
