Metadata-Version: 2.1
Name: astro-gspider
Version: 0.1.1
Summary: A package for GSPIDER
Home-page: https://github.com/shopastro/astro-gspider
Author: GSPIDER
Author-email: qianhuai.ozc@shopastro-inc.com
Classifier: Programming Language :: Python :: 3
Classifier: License :: OSI Approved :: MIT License
Classifier: Operating System :: OS Independent
Requires-Python: >=3.6
License-File: LICENSE
